pykolada/__init__.py
pykolada/pykolada.py
pykolada-1.0.0.dist-info/LICENSE
pykolada-1.0.0.dist-info/METADATA
pykolada-1.0.0.dist-info/WHEEL
pykolada-1.0.0.dist-info/top_level.txt
pykolada-1.0.0.dist-info/RECORD
